Visualizer/__about__.py
Visualizer/__init__.py
Visualizer/keywords/__init__.py
Visualizer/keywords/keywords.py
Visualizer/utils/enums.py
robotframework_visualizer-0.0.10.dist-info/METADATA
robotframework_visualizer-0.0.10.dist-info/WHEEL
robotframework_visualizer-0.0.10.dist-info/licenses/LICENSE
robotframework_visualizer-0.0.10.dist-info/RECORD
