Metadata-Version: 2.4
Name: robotframework-visualizer
Version: 0.0.10
Summary: A Robot Framework library providing keywords for the visualization of 'date / value' objects.
Project-URL: Repository, https://github.com/MarvKler/robotframework-visualizer
Project-URL: Documentation, https://github.com/MarvKler/robotframework-visualizer#readme
Project-URL: Issues, https://github.com/MarvKler/robotframework-visualizer/issues
Project-URL: Keywords, https://marvkler.github.io/robotframework-visualizer/keywords.html
Author-email: Marvin Klerx <marvinklerx20@gmail.com>
License: Apache-2.0
License-File: LICENSE
Classifier: Development Status :: 1 - Planning
Classifier: Programming Language :: Python
Classifier: Programming Language :: Python :: 3.10
Classifier: Programming Language :: Python :: 3.11
Classifier: Programming Language :: Python :: 3.12
Classifier: Programming Language :: Python :: Implementation :: CPython
Classifier: Programming Language :: Python :: Implementation :: PyPy
Requires-Python: >=3.10
Requires-Dist: matplotlib
Requires-Dist: overrides
Requires-Dist: pandas
Requires-Dist: robotframework
Requires-Dist: robotframework-pythonlibcore
Provides-Extra: dev
Requires-Dist: hatch; extra == 'dev'
Requires-Dist: pytest; extra == 'dev'
Requires-Dist: ruff; extra == 'dev'
